renard/gender.py
renard/graph_utils.py
renard/ner_utils.py
renard/nltk_utils.py
renard/plot_utils.py
renard/py.typed
renard/pyvis_template.html
renard/ui.py
renard/utils.py
renard/pipeline/__init__.py
renard/pipeline/character_unification.py
renard/pipeline/characters_extraction.py
renard/pipeline/core.py
renard/pipeline/graph_extraction.py
renard/pipeline/pp.graphml
renard/pipeline/preconfigured.py
renard/pipeline/preprocessing.py
renard/pipeline/progress.py
renard/pipeline/quote_detection.py
renard/pipeline/relation_extraction.py
renard/pipeline/sentiment_analysis.py
renard/pipeline/speaker_attribution.py
renard/pipeline/stanford_corenlp.py
renard/pipeline/tokenization.py
renard/pipeline/corefs/__init__.py
renard/pipeline/corefs/corefs.py
renard/pipeline/ner/__init__.py
renard/pipeline/ner/ner.py
renard/pipeline/ner/retrieval.py
renard/resources/determiners/__init__.py
renard/resources/determiners/determiners.py
renard/resources/hypocorisms/__init__.py
renard/resources/hypocorisms/hypocorisms.py
renard/resources/hypocorisms/datas/License.txt
renard/resources/hypocorisms/datas/hypocorisms.csv
renard/resources/novels/__init__.py
renard/resources/novels/novels.py
renard/resources/novels/pride_and_prejudice/chapter_1.txt
renard/resources/novels/pride_and_prejudice/chapter_10.txt
renard/resources/novels/pride_and_prejudice/chapter_11.txt
renard/resources/novels/pride_and_prejudice/chapter_12.txt
renard/resources/novels/pride_and_prejudice/chapter_13.txt
renard/resources/novels/pride_and_prejudice/chapter_14.txt
renard/resources/novels/pride_and_prejudice/chapter_15.txt
renard/resources/novels/pride_and_prejudice/chapter_16.txt
renard/resources/novels/pride_and_prejudice/chapter_17.txt
renard/resources/novels/pride_and_prejudice/chapter_18.txt
renard/resources/novels/pride_and_prejudice/chapter_19.txt
renard/resources/novels/pride_and_prejudice/chapter_2.txt
renard/resources/novels/pride_and_prejudice/chapter_20.txt
renard_pipeline-0.7.1.dist-info/METADATA
renard_pipeline-0.7.1.dist-info/WHEEL
renard_pipeline-0.7.1.dist-info/licenses/LICENSE
renard_pipeline-0.7.1.dist-info/RECORD
