Metadata-Version: 2.4
Name: renard-pipeline
Version: 0.7.1
Summary: Relationships Extraction from NARrative Documents
Project-URL: Homepage, https://github.com/CompNet/Renard
Project-URL: Documentation, https://compnet.github.io/Renard/
Project-URL: Repository, https://github.com/CompNet/Renard
Author-email: Arthur Amalvy <arthur.amalvy@univ-avignon.fr>
License: GPL-3.0-only
License-File: LICENSE
Requires-Python: <3.13,>=3.9
Requires-Dist: accelerate>=1.10.1
Requires-Dist: datasets>=4.0.0
Requires-Dist: grimbert>=0.1.5
Requires-Dist: matplotlib>=3.9
Requires-Dist: more-itertools>=10.7
Requires-Dist: nameparser>=1.1.3
Requires-Dist: networkx>=3.2
Requires-Dist: nltk>=3.9.1
Requires-Dist: protobuf>=6.33.2
Requires-Dist: pytest>=8.4.1
Requires-Dist: rank-bm25>=0.2.2
Requires-Dist: scikit-learn>=1.6.1
Requires-Dist: tibert>=0.5.2
Requires-Dist: tiktoken>=0.12.0
Requires-Dist: torch>=2.7.0
Requires-Dist: tqdm>=4.67.1
Requires-Dist: transformers>=4.57.1
Provides-Extra: cpu
Requires-Dist: torch>=2.7.1; extra == 'cpu'
Provides-Extra: cuda128
Requires-Dist: torch>=2.7.1; extra == 'cuda128'
Provides-Extra: rocm63
Requires-Dist: pytorch-triton-rocm>=3.1.0; extra == 'rocm63'
Requires-Dist: torch>=2.7.1; extra == 'rocm63'
Provides-Extra: rocm64
Requires-Dist: pytorch-triton-rocm>=3.1.0; extra == 'rocm64'
Requires-Dist: torch>=2.7.1; extra == 'rocm64'
Provides-Extra: ui
Requires-Dist: gradio>=4.44.1; extra == 'ui'
Requires-Dist: pyvis>=0.3.2; extra == 'ui'
